{
  "$schema": "http://json-schema.org/draft-04/schema#",
  "id": "https://schema.github.com/v3/code-of-conduct-simple.json",
  "title": "Code Of Conduct Simple",
  "type": "object",
  "definitions": {
    "url": {
      "type": "string",
      "format": "uri",
      "example": "https://api.github.com/codes_of_conduct/citizen_code_of_conduct"
    },
    "key": {
      "type": "string",
      "example": "citizen_code_of_conduct"
    },
    "name": {
      "type": "string",
      "example": "Citizen Code of Conduct"
    },
    "html_url": {
      "type": [
        "string",
        "null"
      ],
      "format": "uri"
    }
  },
  "properties": {
    "url": {
      "$ref": "#/definitions/url"
    },
    "key": {
      "$ref": "#/definitions/key"
    },
    "name": {
      "$ref": "#/definitions/name"
    },
    "html_url": {
      "$ref": "#/definitions/html_url"
    }
  },
  "additionalProperties": false,
  "required": [
    "url",
    "key",
    "name",
    "html_url"
  ]
}
