{
  "$schema": "http://json-schema.org/draft-04/schema#",
  "id": "https://schema.github.com/v3/collaborator-plus-identity.json",
  "title": "Collaborator Plus Identity",
  "type": "object",
  "definitions": {
    "avatar_url": {
      "type": "string",
      "format": "uri"
    },
    "events_url": {
      "type": "string"
    },
    "followers_url": {
      "type": "string",
      "format": "uri"
    },
    "following_url": {
      "type": "string"
    },
    "gists_url": {
      "type": "string"
    },
    "gravatar_id": {
      "type": [
        "string",
        "null"
      ]
    },
    "html_url": {
      "type": "string",
      "format": "uri"
    },
    "id": {
      "type": "integer"
    },
    "node_id": {
      "type": "string"
    },
    "login": {
      "type": "string"
    },
    "organizations_url": {
      "type": "string",
      "format": "uri"
    },
    "received_events_url": {
      "type": "string",
      "format": "uri"
    },
    "repos_url": {
      "type": "string",
      "format": "uri"
    },
    "site_admin": {
      "type": "boolean"
    },
    "starred_url": {
      "type": "string"
    },
    "subscriptions_url": {
      "type": "string",
      "format": "uri"
    },
    "type": {
      "type": "string"
    },
    "url": {
      "type": "string",
      "format": "uri"
    },
    "email": {
      "type": [
        "string",
        "null"
      ],
      "format": "email"
    },
    "name": {
      "type": [
        "string",
        "null"
      ]
    }
  },
  "properties": {
    "avatar_url": {
      "$ref": "#/definitions/avatar_url"
    },
    "events_url": {
      "$ref": "#/definitions/events_url"
    },
    "followers_url": {
      "$ref": "#/definitions/followers_url"
    },
    "following_url": {
      "$ref": "#/definitions/following_url"
    },
    "gists_url": {
      "$ref": "#/definitions/gists_url"
    },
    "gravatar_id": {
      "$ref": "#/definitions/gravatar_id"
    },
    "html_url": {
      "$ref": "#/definitions/html_url"
    },
    "id": {
      "$ref": "#/definitions/id"
    },
    "node_id": {
      "$ref": "#/definitions/node_id"
    },
    "login": {
      "$ref": "#/definitions/login"
    },
    "organizations_url": {
      "$ref": "#/definitions/organizations_url"
    },
    "received_events_url": {
      "$ref": "#/definitions/received_events_url"
    },
    "repos_url": {
      "$ref": "#/definitions/repos_url"
    },
    "site_admin": {
      "$ref": "#/definitions/site_admin"
    },
    "starred_url": {
      "$ref": "#/definitions/starred_url"
    },
    "subscriptions_url": {
      "$ref": "#/definitions/subscriptions_url"
    },
    "type": {
      "$ref": "#/definitions/type"
    },
    "url": {
      "$ref": "#/definitions/url"
    },
    "permissions": {
      "type": "object",
      "properties": {
        "pull": {
          "type": "boolean"
        },
        "triage": {
          "type": "boolean"
        },
        "push": {
          "type": "boolean"
        },
        "maintain": {
          "type": "boolean"
        },
        "admin": {
          "type": "boolean"
        }
      },
      "additionalProperties": false,
      "required": [
        "pull",
        "triage",
        "push",
        "maintain",
        "admin"
      ]
    },
    "role_name": {
      "type": "string"
    },
    "email": {
      "$ref": "#/definitions/email"
    },
    "name": {
      "$ref": "#/definitions/name"
    }
  },
  "additionalProperties": false,
  "required": [
    "avatar_url",
    "events_url",
    "followers_url",
    "following_url",
    "gists_url",
    "gravatar_id",
    "html_url",
    "id",
    "node_id",
    "login",
    "organizations_url",
    "received_events_url",
    "repos_url",
    "site_admin",
    "starred_url",
    "subscriptions_url",
    "type",
    "url",
    "email",
    "name"
  ]
}
